{
  "type": "minecraft:entity",
  "pools": [
    {
      "rolls": 1,
      "entries": [
        {
          "type": "minecraft:item",
          "name": "minecraft:sculk_catalyst"
        }
      ]
    },
    {
      "rolls": 1,
      "entries": [
        {
          "type": "minecraft:item",
          "name": "minecraft:firework_star",
          "functions": [
            {
              "function": "minecraft:set_nbt",
              "tag": "{Strange:1, display:{Name:'\"Странный орган\"', Lore: ['\"Интересно, для чего это?\"']}}"
            }
          ],
          "conditions": [
            {
              "condition": "minecraft:killed_by_player"
            }
          ]
        }
      ]
    }
  ]
}